{
  "verification_confidence": 9,
  "verdict": "accept",
  "issues_found": [],
  "human_review_required": false,
  "human_review_reason": "The generated record is accurate and appropriately flags all issues with this source. It correctly identifies the source as a listing/navigation page (per Rule 5), notes the missing URL and empty published_at, and correctly suggests rejection. No human review needed as the record itself is well-verified.",
  "suggested_status": "rejected",
  "corrected_fields": {
    "summary": "",
    "why_it_matters": "",
    "macro_context": "",
    "market_structure_context": ""
  }
}