{
  "verification_confidence": 0,
  "verdict": "reject",
  "issues_found": [
    "Source is a listing/navigation page (source_type: listing_page) - per Rule 5, reject pages of this type",
    "No substantive research content present - only generic description of staff research activities",
    "No specific publication dates, titles, or findings provided",
    "Cannot assess relevance to market structure or macro catalysts as page contains no actionable content",
    "event_type set to 'unknown' when the correct classification (listing_page) is obvious from context",
    "Source is a thin, low-signal page with no archival value per Rule 6"
  ],
  "human_review_required": false,
  "human_review_reason": "Record already includes comprehensive human review with clear reject recommendation. Source is unambiguously a listing page with no substantive content. Automated routing to reject is appropriate.",
  "suggested_status": "rejected",
  "corrected_fields": {
    "summary": "",
    "why_it_matters": "",
    "macro_context": "",
    "market_structure_context": ""
  }
}