{
  "verification_confidence": 0,
  "verdict": "reject",
  "issues_found": [
    "Source is a navigation/listing page with no substantive content about quarterly refunding operations",
    "source_type correctly identified as 'navigation_page' which triggers rejection per Rule 5",
    "published_at is empty in source metadata, making age assessment impossible",
    "Actual substantive content (auction details, issuance amounts, financing plans) exists only on linked sub-pages, not in this source",
    "Summary is accurate but confirms the source has no archival value for market structure research"
  ],
  "human_review_required": false,
  "human_review_reason": "",
  "suggested_status": "rejected",
  "corrected_fields": {
    "summary": "",
    "why_it_matters": "",
    "macro_context": "",
    "market_structure_context": ""
  }
}