{
  "event_id": "event_seed_crawl_newyorkfed_household_",
  "title": "ny fed / consumer expectations / household spending | Data Release Other | Household Survey Shows Reported and Expected Household Spend...",
  "topic": "macro catalysts",
  "event_type": "data_release_other",
  "summary": "The December 2023 Survey of Consumer Expectations shows median monthly household spending growth declined to 5.0% (from 7.1% a year prior), while year-ahead spending expectations fell to 3.0%, the lowest since December 2020. Notably, households report they would allocate 38.4% of an unexpected 10% income increase to debt paydown (highest since 2016), while only 16.0% would be spent or donated (lowest since the series began in 2015).",
  "status": "open",
  "created_at": "2026-04-10T06:27:32.008895Z",
  "updated_at": "2026-04-10T06:27:32.008895Z",
  "record_ids": [
    "seed_crawl_newyorkfed_household_survey_shows_reported_and_78905f4ca7a4f310"
  ],
  "source_domains": [
    "www.newyorkfed.org"
  ],
  "keywords": [
    "ny-fed",
    "consumer-expectations",
    "household-spending",
    "sce-survey",
    "consumer-caution",
    "disinflation",
    "debt-paydown",
    "consumer-sentiment"
  ],
  "quant_links": [],
  "confidence": 1.0
}