{
  "event_id": "event_bank_of_canada_press_browse_mone",
  "title": "bank of canada / monetary policy report / policy rate | Monetary Policy Report | Monetary Policy Report—January 2026",
  "topic": "macro catalysts",
  "event_type": "monetary_policy_report",
  "summary": "The Bank of Canada released its January 2026 Monetary Policy Report maintaining the overnight policy rate at 2.25%, with the Bank Rate at 2.5% and deposit rate at 2.20%. US tariffs and trade uncertainty continue to disrupt the Canadian economy, with growth projected to average around 1¼% over the projection horizon while inflation remains near the 2% target.",
  "status": "open",
  "created_at": "2026-04-10T05:40:18.050546Z",
  "updated_at": "2026-04-10T05:40:18.050546Z",
  "record_ids": [
    "bank_of_canada_press_browse_monetary_policy_report_january_2026_bank_of_canada_450527af"
  ],
  "source_domains": [
    "www.bankofcanada.ca"
  ],
  "keywords": [
    "bank of canada",
    "monetary policy report",
    "policy rate",
    "canada economy",
    "us tariffs",
    "trade uncertainty",
    "cpi inflation",
    "cusma",
    "north american trade"
  ],
  "quant_links": [],
  "confidence": 1.0
}