{
  "event_id": "event_keyword_discovery_ecb.europa_pdf",
  "title": "ecb / monetary policy / inflation outlook | Monetary Policy Report | Economic Bulletin Issue 2, 2026",
  "topic": "macro catalysts",
  "event_type": "monetary_policy_report",
  "summary": "At its March 19, 2026 meeting, the ECB Governing Council kept its three key ECB interest rates unchanged, maintaining its commitment to ensure inflation stabilises at the 2% target in the medium term. Staff macroeconomic projections show headline inflation revised up to 2.6% in 2026 (from December 2025 projections), while GDP growth was revised down to 0.9% in 2026, reflecting the disruptive impact of the Middle East war on commodity markets, real incomes, and confidence.",
  "status": "open",
  "created_at": "2026-04-11T05:25:39.289966Z",
  "updated_at": "2026-04-11T05:25:39.289966Z",
  "record_ids": [
    "keyword_discovery_ecb.europa_pdf_economic_bulletin_issue_2_e4f0e359a41414b6"
  ],
  "source_domains": [
    "www.ecb.europa.eu"
  ],
  "keywords": [
    "ecb",
    "monetary-policy",
    "inflation-outlook",
    "growth-projections",
    "middle-east-conflict",
    "energy-prices",
    "euro-area",
    "rate-decision-unchanged"
  ],
  "quant_links": [],
  "confidence": 1.0
}